hub/__init__.py
hub_redirect-3.0.3.dist-info/METADATA
hub_redirect-3.0.3.dist-info/WHEEL
hub_redirect-3.0.3.dist-info/top_level.txt
hub_redirect-3.0.3.dist-info/RECORD
