Metadata-Version: 2.1
Name: hub-redirect
Version: 3.0.3
Summary: Activeloop Deep Lake
Home-page: https://www.github.com/activeloopai/deeplake
Author: activeloop.ai
Author-email: support@activeloop.ai
Requires-Dist: deeplake
